piecewise_distortion/__init__.py
piecewise_distortion/piecewise_distortion.py
piecewise_distortion-0.1.dist-info/DESCRIPTION.rst
piecewise_distortion-0.1.dist-info/METADATA
piecewise_distortion-0.1.dist-info/RECORD
piecewise_distortion-0.1.dist-info/WHEEL
piecewise_distortion-0.1.dist-info/metadata.json
piecewise_distortion-0.1.dist-info/top_level.txt
