Metadata-Version: 2.0
Name: piecewise-distortion
Version: 0.1
Summary: A package to manage image distortion
Home-page: https://github.com/SUKOHI
Author: sukohi
Author-email: sukohi.capilano@gmail.com
License: MIT
Keywords: distort image
Platform: UNKNOWN
Requires-Dist: numpy
Requires-Dist: pillow
Requires-Dist: scikit-image
